CHANGES.txt
DEPENDENCES.txt
README.txt
setup.py
src/ng/__init__.py
src/ng.index.topology.egg-info/PKG-INFO
src/ng.index.topology.egg-info/SOURCES.txt
src/ng.index.topology.egg-info/dependency_links.txt
src/ng.index.topology.egg-info/namespace_packages.txt
src/ng.index.topology.egg-info/not-zip-safe
src/ng.index.topology.egg-info/requires.txt
src/ng.index.topology.egg-info/top_level.txt
src/ng/index/__init__.py
src/ng/index/topology/__init__.py
src/ng/index/topology/configure.zcml
src/ng/index/topology/interfaces.py
src/ng/index/topology/ng.index.topology.txt
src/ng/index/topology/topologybase.py
src/ng/index/topology/topologycontainer.py
src/ng/index/topology/topologyhandler.py
src/ng/index/topology/topologyindex.py
src/ng/index/topology/topologyitem.py
src/ng/index/topology/topologyitemvocabulary.py
src/ng/index/topology/browser/__init__.py
src/ng/index/topology/browser/configure.zcml
src/ng/index/topology/etc/ng.index.topology-configure.zcml